odoo/addons/mrp_stock_orderpoint_manual_procurement/README.rst
odoo/addons/mrp_stock_orderpoint_manual_procurement/__init__.py
odoo/addons/mrp_stock_orderpoint_manual_procurement/__manifest__.py
odoo/addons/mrp_stock_orderpoint_manual_procurement/i18n/mrp_stock_orderpoint_manual_procurement.pot
odoo/addons/mrp_stock_orderpoint_manual_procurement/models/__init__.py
odoo/addons/mrp_stock_orderpoint_manual_procurement/models/mrp_production.py
odoo/addons/mrp_stock_orderpoint_manual_procurement/models/procurement.py
odoo/addons/mrp_stock_orderpoint_manual_procurement/readme/CONTRIBUTORS.rst
odoo/addons/mrp_stock_orderpoint_manual_procurement/readme/DESCRIPTION.rst
odoo/addons/mrp_stock_orderpoint_manual_procurement/readme/USAGE.rst
odoo/addons/mrp_stock_orderpoint_manual_procurement/static/description/icon.png
odoo/addons/mrp_stock_orderpoint_manual_procurement/static/description/index.html
odoo/addons/mrp_stock_orderpoint_manual_procurement/tests/__init__.py
odoo/addons/mrp_stock_orderpoint_manual_procurement/tests/test_mrp_manual_procurement.py
odoo/addons/mrp_stock_orderpoint_manual_procurement/views/mrp_production_view.xml
odoo11_addon_mrp_stock_orderpoint_manual_procurement-11.0.1.0.0.99.dev4.dist-info/METADATA
odoo11_addon_mrp_stock_orderpoint_manual_procurement-11.0.1.0.0.99.dev4.dist-info/WHEEL
odoo11_addon_mrp_stock_orderpoint_manual_procurement-11.0.1.0.0.99.dev4.dist-info/top_level.txt
odoo11_addon_mrp_stock_orderpoint_manual_procurement-11.0.1.0.0.99.dev4.dist-info/RECORD
